condansis/__init__.py
condansis/_version.py
condansis/installer.py
condansis/installer_template.nsi
condansis/sitecustomize.py
condansis/test_installer.py
condansis/test_files/environment.yml
condansis-0.3.2.dist-info/LICENSE.txt
condansis-0.3.2.dist-info/METADATA
condansis-0.3.2.dist-info/WHEEL
condansis-0.3.2.dist-info/top_level.txt
condansis-0.3.2.dist-info/RECORD
