Metadata-Version: 2.1
Name: condansis
Version: 0.3.2
Summary: Create installers for Python packages using NSIS and Conda
Home-page: http://guilhermebs.github.io/condansis
Author: Guilherme Saturnino
Author-email: GUISA@orsted.dk
License: UNKNOWN
Keywords: packaging,installer,windows
Platform: UNKNOWN
Classifier: Development Status :: 3 - Alpha
Classifier: Environment :: Win32 (MS Windows)
Classifier: Intended Audience :: Developers
Classifier: Topic :: Software Development :: Build Tools
Classifier: Programming Language :: Python :: 3 :: Only
Requires-Python: >=3.5, <4
Requires-Dist: conda-pack (>=0.5)
Requires-Dist: jinja2
Provides-Extra: test
Requires-Dist: pytest ; extra == 'test'
